Metadata-Version: 1.0
Name: ibytes
Version: 1.2
Summary: Network stream processing tools
Home-page: https://github.com/scp10011/ibytes
Author: scp10011
Author-email: circlelbw@hotmail.com
License: UNKNOWN
Platform: UNKNOWN
